{"cameraMode":{"drawMode":0,"name":"Shaded","section":"Shading Mode"},"sceneLighting":false,"audioPlay":false,"sceneViewState":{"showFog":true,"showMaterialUpdate":false,"showSkybox":false,"showFlares":true,"showImageEffects":true,"showParticleSystems":true},"in2DMode":false,"pivot":{"x":-0.02463788352906704,"y":-0.04450840502977371,"z":0.0},"rotation":{"x":-0.3443135619163513,"y":-0.06891873478889466,"z":-0.025352705270051957,"w":0.935980498790741},"size":36.077003479003909,"orthographic":false}